simplebook/__init__.py
simplebook/__main__.py
simplebook/cli.py
simplebook/config.py
simplebook/main.py
simplebook/output_schema.json
simplebook/schema_validator.py
simplebook-0.1.0.dist-info/licenses/LICENSE
simplebook-0.1.0.dist-info/METADATA
simplebook-0.1.0.dist-info/WHEEL
simplebook-0.1.0.dist-info/entry_points.txt
simplebook-0.1.0.dist-info/top_level.txt
simplebook-0.1.0.dist-info/RECORD
