Metadata-Version: 2.4
Name: simplebook
Version: 0.1.0
Summary: Deterministic EPUB normalizer and tooling.
Author-email: Bradley Fallon <bradley.fallon@gmail.com>
License: MIT License
Project-URL: Homepage, https://github.com/BradleyFallon/SimpleBook
Project-URL: Repository, https://github.com/BradleyFallon/SimpleBook
Classifier: Development Status :: 3 - Alpha
Classifier: Intended Audience :: Developers
Classifier: License :: OSI Approved :: MIT License
Classifier: Programming Language :: Python :: 3
Classifier: Programming Language :: Python :: 3.10
Classifier: Programming Language :: Python :: 3.11
Classifier: Programming Language :: Python :: 3.12
Requires-Python: >=3.10
License-File: LICENSE
Requires-Dist: ebooklib>=0.18
Requires-Dist: beautifulsoup4>=4.12.0
Requires-Dist: lxml>=4.9.0
Requires-Dist: jsonschema>=4.0.0
Provides-Extra: dev
Requires-Dist: pytest>=7.0.0; extra == "dev"
Requires-Dist: hypothesis>=6.0.0; extra == "dev"
Requires-Dist: black>=24.0.0; extra == "dev"
Requires-Dist: ruff>=0.5.0; extra == "dev"
Requires-Dist: pyright>=1.1.0; extra == "dev"
Requires-Dist: tox>=4.0.0; extra == "dev"
Requires-Dist: coverage>=7.0.0; extra == "dev"
Requires-Dist: pylint>=3.0.0; extra == "dev"
Dynamic: license-file
